app_transport_framework_library/__init__.py
app_transport_framework_library/atf_bundle_processor.py
app_transport_framework_library/base_use_case_validator.py
app_transport_framework_library/models/bundle_content.py
app_transport_framework_library/models/empfangsbestaetigung.py
app_transport_framework_library/models/event.py
app_transport_framework_library/models/message_to_send.py
app_transport_framework_library/models/service_identifier.py
app_transport_framework_library/ressource_creators/message_bundle_creator.py
app_transport_framework_library/ressource_creators/message_header_creator.py
app_transport_framework_library/ressource_creators/operation_outcome_bundle_creator.py
app_transport_framework_library/ressource_creators/operation_outcome_creator.py
app_transport_framework_library/ressource_creators/test_message_creator.py
app_transport_framework_library/use_cases/empfangsbestaetigung_handler.py
app_transport_framework_library/use_cases/selbsttest_lieferung_validator.py
app_transport_framework_library-0.1.12.dist-info/METADATA
app_transport_framework_library-0.1.12.dist-info/WHEEL
app_transport_framework_library-0.1.12.dist-info/RECORD
