Metadata-Version: 2.1
Name: app-transport-framework-library
Version: 0.1.12
Summary: 
Author: Sven Sommer
Author-email: rob.hoffmann@posteo.de
Requires-Python: >=3.8,<4.0
Classifier: Programming Language :: Python :: 3
Classifier: Programming Language :: Python :: 3.8
Classifier: Programming Language :: Python :: 3.9
Classifier: Programming Language :: Python :: 3.10
Classifier: Programming Language :: Python :: 3.11
Classifier: Programming Language :: Python :: 3.12
Requires-Dist: fhir-resources (==7.1.0)
